superagentx/__init__.py
superagentx/agent.py
superagentx/agentxpipe.py
superagentx/base.py
superagentx/browser_engine.py
superagentx/channels/__init__.py
superagentx/channels/base.py
superagentx/channels/console_channel.py
superagentx/channels/slack_channel.py
superagentx/channels/teams_channel.py
superagentx/computer_use/__init__.py
superagentx/computer_use/browser/__init__.py
superagentx/computer_use/browser/browser.py
superagentx/computer_use/browser/context.py
superagentx/computer_use/browser/dom/__init__.py
superagentx/computer_use/browser/dom/clickable_element_processor/service.py
superagentx/computer_use/browser/dom/dom_builder.js
superagentx/computer_use/browser/dom/dom_service.py
superagentx/computer_use/browser/dom/history_tree_processor/__init__.py
superagentx/computer_use/browser/dom/history_tree_processor/tree_processor_service.py
superagentx/computer_use/browser/dom/history_tree_processor/view.py
superagentx/computer_use/browser/dom/views.py
superagentx/computer_use/browser/models.py
superagentx/computer_use/browser/state.py
superagentx/computer_use/constants.py
superagentx/computer_use/desktop/__init__.py
superagentx/computer_use/utils.py
superagentx/config.py
superagentx/constants.py
superagentx/db_store/__init__.py
superagentx/db_store/db_interface.py
superagentx/db_store/db_storage.py
superagentx/db_store/sql_status_enum.py
superagentx/engine.py
superagentx/exceptions.py
superagentx/handler/__init__.py
superagentx/handler/ai.py
superagentx/handler/base.py
superagentx/handler/browser.py
superagentx/handler/decorators.py
superagentx/handler/elastic_search.py
superagentx/handler/exa_search.py
superagentx/handler/exceptions.py
superagentx/handler/financial_data.py
superagentx/handler/mcp.py
superagentx/handler/openapi.py
superagentx/handler/send_email.py
superagentx/handler/serper_dev.py
superagentx/handler/task/__init__.py
superagentx/handler/task/general/__init__.py
superagentx/handler/task/general/api_handler.py
superagentx-1.0.5.1.dist-info/METADATA
superagentx-1.0.5.1.dist-info/WHEEL
superagentx-1.0.5.1.dist-info/entry_points.txt
superagentx-1.0.5.1.dist-info/licenses/LICENSE
superagentx-1.0.5.1.dist-info/RECORD
