Metadata-Version: 2.4
Name: superagentx
Version: 1.0.5.1
Summary: The Ultimate Modular Autonomous Multi AI Agent Framework.
License: MIT
License-File: LICENSE
Keywords: superagentX,AGI,Agentic AI,ASI,superagentx,agent,LLM,cli
Author: SuperAgentX AI
Author-email: <support@superagentx.ai>
Maintainer: SuperAgentX AI
Maintainer-email: <support@superagentx.ai>
Requires-Python: >=3.12,<=3.13
Classifier: License :: OSI Approved :: MIT License
Classifier: Programming Language :: Python :: 3
Classifier: Programming Language :: Python :: 3.12
Classifier: Programming Language :: Python :: 3.13
Provides-Extra: all
Provides-Extra: cli
Requires-Dist: SQLAlchemy (>=2.0.45)
Requires-Dist: aiofiles (>=24.1.0)
Requires-Dist: aiohttp (>=3.10.8)
Requires-Dist: aiopath (==0.7.7)
Requires-Dist: aiosqlite (>=0.20.0)
Requires-Dist: asyncpg (>=0.31.0)
Requires-Dist: bokeh (>=3.7.3) ; extra == "all"
Requires-Dist: boto3 (>=1.35.8) ; extra == "all"
Requires-Dist: camel-converter (>=4.0.1)
Requires-Dist: chromadb (>=1.0.10) ; extra == "all"
Requires-Dist: elasticsearch (>=9.0.1) ; extra == "all"
Requires-Dist: exa-py (>=1.1.4)
Requires-Dist: fastembed (>=0.6.0) ; extra == "all"
Requires-Dist: google-genai (>=1.20.0) ; extra == "all"
Requires-Dist: httpx (>=0.28.1,<0.29.0)
Requires-Dist: importlib-resources (>=6.5.2)
Requires-Dist: jinja2 (>=3.1.4) ; extra == "all"
Requires-Dist: jinja2 (>=3.1.4) ; extra == "cli"
Requires-Dist: litellm (>=1.79.0)
Requires-Dist: markdownify (>=1.1.0)
Requires-Dist: mcp (>=1.7.0,<2.0.0)
Requires-Dist: neo4j (>=5.28.1) ; extra == "all"
Requires-Dist: ntplib (>=0.4.0)
Requires-Dist: numpy (>=2.2.6) ; extra == "all"
Requires-Dist: ollama (>=0.4.7) ; extra == "all"
Requires-Dist: openai (>=1.47.1)
Requires-Dist: opensearch-py (>=2.8.0) ; extra == "all"
Requires-Dist: opentelemetry-exporter-otlp-proto-grpc (>=1.33.1) ; extra == "all"
Requires-Dist: playwright (>=1.52.0)
Requires-Dist: psutil (>=7.0.0)
Requires-Dist: pydantic (>=2.8.2)
Requires-Dist: pyotp (>=2.9.0)
Requires-Dist: pyyaml (>=6.0.2)
Requires-Dist: rich (>=13.9.2)
Requires-Dist: rich (>=13.9.2) ; extra == "all"
Requires-Dist: rich (>=13.9.2) ; extra == "cli"
Requires-Dist: scipy (>=1.15.3) ; extra == "all"
Requires-Dist: typer (>=0.13.0) ; extra == "all"
Requires-Dist: typer (>=0.13.0) ; extra == "cli"
Requires-Dist: websockets (>=15.0.1,<16.0.0)
Requires-Dist: yapf (>=0.43.0) ; extra == "all"
Requires-Dist: yapf (>=0.43.0) ; extra == "cli"
Requires-Dist: yapf (>=0.43.0,<0.44.0)
Project-URL: Documentation, https://docs.superagentx.ai/
Project-URL: Homepage, https://www.superagentx.ai/
Project-URL: Repository, https://github.com/superagentxai/superagentx
